{
    "frosh-mail-archive": {
        "title": "Mail Archive",
        "state": {
            "pending": "pending",
            "sent": "sent",
            "failed": "failed",
            "unknown": "unknown"
        },
        "list": {
            "columns": {
                "sentDate": "Sent date",
                "subject": "Subject",
                "receiver": "Recipients",
                "action": "Show",
                "transportState": "State",
                "transportFailed": "Mail delivery failed."
            },
            "sidebar": {
                "refresh": "Refresh",
                "filter": "Filter",
                "filters": {
                    "search": "Search",
                    "customer": "Customer",
                    "salesChannel": "Sales Channel",
                    "transportStateLabel": "State",
                    "transportStatePlaceholder": "Select state",
                    "resetFilter": "Reset filter"
                }
            }
        },
        "detail": {
            "toolbar": {
                "customer": "Open customer",
                "resend": "Resend mail",
                "downloadEml": "Download mail"
            },
            "metadata": {
                "title": "Metadata",
                "sentDate": "Sent date",
                "sender": "Sender",
                "receiver": "Recipients",
                "subject": "Subject",
                "salesChannel": "Sales Channel"
            },
            "content": {
                "title": "Content"
            },
            "alert": {
                "transportFailed": "Mail delivery failed. Please check mailer settings and try again."
            },
            "resend-success-notification": {
                "message": "Mail dispatch has started.",
                "title": "Mail Archive"
            },
            "resend-error-notification": {
                "title": "Mail Archive",
                "message": "Mail could not be delivered"
            },
            "resend-grid": {
                "navigate": "Show",
                "column-created-at": "Sent at",
                "column-state": "State",
                "currently-selected": "this",
                "title": "Resend history"
            }
        }
    }
}
